LICENSE
README.md
pyproject.toml
setup.cfg
setup.py
yenepay/__init__.py
yenepay/api.py
yenepay/constants.py
yenepay/exceptions.py
yenepay/helpers.py
yenepay.egg-info/PKG-INFO
yenepay.egg-info/SOURCES.txt
yenepay.egg-info/dependency_links.txt
yenepay.egg-info/requires.txt
yenepay.egg-info/top_level.txt
yenepay/models/__init__.py
yenepay/models/checkout.py
yenepay/models/client.py
yenepay/models/ipn.py
yenepay/models/pdt.py